{
    "status": "success",
    "data": [
      {
        "date": "2024-01-01",
        "title": "Año Nuevo",
        "type": "Civil",
        "inalienable": true,
        "extra": "Civil e Irrenunciable"
      },
      {
        "date": "2024-03-29",
        "title": "Viernes Santo",
        "type": "Religioso",
        "inalienable": false,
        "extra": "Religioso"
      },
      {
        "date": "2024-03-30",
        "title": "Sábado Santo",
        "type": "Religioso",
        "inalienable": false,
        "extra": "Religioso"
      },
      {
        "date": "2024-05-01",
        "title": "Día Nacional del Trabajo",
        "type": "Civil",
        "inalienable": true,
        "extra": "Civil e Irrenunciable"
      },
      {
        "date": "2024-05-21",
        "title": "Día de las Glorias Navales",
        "type": "Civil",
        "inalienable": false,
        "extra": "Civil"
      },
      {
        "date": "2024-06-09",
        "title": "Elecciones Primarias Alcaldes y Gobernadores",
        "type": "Civil",
        "inalienable": false,
        "extra": "Civil"
      },
      {
        "date": "2024-06-20",
        "title": "Día Nacional de los Pueblos Indígenas",
        "type": "Civil",
        "inalienable": false,
        "extra": "Civil"
      },
      {
        "date": "2024-06-29",
        "title": "San Pedro y San Pablo",
        "type": "Religioso",
        "inalienable": false,
        "extra": "Religioso"
      },
      {
        "date": "2024-07-16",
        "title": "Día de la Virgen del Carmen",
        "type": "Religioso",
        "inalienable": false,
        "extra": "Religioso"
      },
      {
        "date": "2024-08-15",
        "title": "Asunción de la Virgen",
        "type": "Religioso",
        "inalienable": false,
        "extra": "Religioso"
      },
      {
        "date": "2024-09-18",
        "title": "Independencia Nacional",
        "type": "Civil",
        "inalienable": true,
        "extra": "Civil e Irrenunciable"
      },
      {
        "date": "2024-09-19",
        "title": "Día de las Glorias del Ejército",
        "type": "Civil",
        "inalienable": true,
        "extra": "Civil e Irrenunciable"
      },
      {
        "date": "2024-09-20",
        "title": "Feriado Adicional Fiestas Patrias",
        "type": "Civil",
        "inalienable": false,
        "extra": "Civil"
      },
      {
        "date": "2024-10-12",
        "title": "Encuentro de Dos Mundos",
        "type": "Civil",
        "inalienable": false,
        "extra": "Civil"
      },
      {
        "date": "2024-10-27",
        "title": "Elecciones Municipales, Consejeros Regionales y Gobernadores Regionales",
        "type": "Civil",
        "inalienable": true,
        "extra": "Civil e Irrenunciable"
      },
      {
        "date": "2024-10-31",
        "title": "Día de las Iglesias Evangélicas y Protestantes",
        "type": "Religioso",
        "inalienable": false,
        "extra": "Religioso"
      },
      {
        "date": "2024-11-01",
        "title": "Día de Todos los Santos",
        "type": "Religioso",
        "inalienable": false,
        "extra": "Religioso"
      },
      {
        "date": "2024-11-24",
        "title": "Segunda Vuelta Elección Gobernadores Regionales",
        "type": "Civil",
        "inalienable": true,
        "extra": "Civil e Irrenunciable"
      },
      {
        "date": "2024-12-08",
        "title": "Inmaculada Concepción",
        "type": "Religioso",
        "inalienable": false,
        "extra": "Religioso"
      },
      {
        "date": "2024-12-25",
        "title": "Navidad",
        "type": "Religioso",
        "inalienable": true,
        "extra": "Religioso e Irrenunciable"
      }
    ]
  }